HLISA/__init__.py
HLISA/additional_actions.py
HLISA/constants.py
HLISA/errors.py
HLISA/hlisa_action_chains.py
HLISA/selenium_actions.py
HLISA/util.py
HLISA-1.6.1.dist-info/LICENSE
HLISA-1.6.1.dist-info/METADATA
HLISA-1.6.1.dist-info/WHEEL
HLISA-1.6.1.dist-info/top_level.txt
HLISA-1.6.1.dist-info/RECORD
