Metadata-Version: 2.1
Name: HLISA
Version: 1.6.1
Summary: A reimplementation of the Selenium API, emulating human interactions
Home-page: https://github.com/droefs/HLISA
Author: David Roefs
License: GPLv3
Project-URL: Bug Tracker, https://github.com/droefs/HLISA/issues
Classifier: Programming Language :: Python :: 3
Classifier: License :: OSI Approved :: GNU General Public License v3 (GPLv3)
Classifier: Operating System :: OS Independent
Requires-Python: >=3.4
License-File: LICENSE
Requires-Dist: selenium
Requires-Dist: numpy
